[{"id":"6401","nama":"Kabupaten Paser","latitude":0,"longitude":0},{"id":"6402","nama":"Kabupaten Kutai Kartanegara","latitude":0,"longitude":0},{"id":"6403","nama":"Kabupaten Berau","latitude":0,"longitude":0},{"id":"6407","nama":"Kabupaten Kutai Barat","latitude":0,"longitude":0},{"id":"6408","nama":"Kabupaten Kutai Timur","latitude":0,"longitude":0},{"id":"6409","nama":"Kabupaten Penajam Paser Utara","latitude":0,"longitude":0},{"id":"6411","nama":"Kabupaten Mahakam Ulu","latitude":0,"longitude":0},{"id":"6471","nama":"Kota Balikpapan","latitude":0,"longitude":0},{"id":"6472","nama":"Kota Samarinda","latitude":0,"longitude":0},{"id":"6474","nama":"Kota Bontang","latitude":0,"longitude":0}]