[{"id":"5310172001","nama":"Bere","latitude":0,"longitude":0},{"id":"5310172002","nama":"Wae Codi","latitude":0,"longitude":0},{"id":"5310172003","nama":"Golo Woi","latitude":0,"longitude":0},{"id":"5310172004","nama":"Golo Lanak","latitude":0,"longitude":0},{"id":"5310172005","nama":"Latung","latitude":0,"longitude":0},{"id":"5310172006","nama":"Wae Renca","latitude":0,"longitude":0},{"id":"5310172007","nama":"Timbu","latitude":0,"longitude":0},{"id":"5310172008","nama":"Bangka Ara","latitude":0,"longitude":0},{"id":"5310172009","nama":"Compang Cibal","latitude":0,"longitude":0},{"id":"5310172010","nama":"Lenda","latitude":0,"longitude":0}]