[{"id":"6107102001","nama":"Nangka","latitude":0,"longitude":0},{"id":"6107102002","nama":"Muhi Bersatu","latitude":0,"longitude":0},{"id":"6107102003","nama":"Suka Maju","latitude":0,"longitude":0},{"id":"6107102004","nama":"Cempaka Putih","latitude":0,"longitude":0},{"id":"6107102005","nama":"Kiung","latitude":0,"longitude":0},{"id":"6107102006","nama":"Kelayuk","latitude":0,"longitude":0},{"id":"6107102007","nama":"Suti Semarang","latitude":0,"longitude":0},{"id":"6107102008","nama":"Tapen","latitude":0,"longitude":0}]