[{"id":"7309112001","nama":"Tompobulu","latitude":-5.1366865648,"longitude":119.6987613201},{"id":"7309112002","nama":"Benteng Gajah","latitude":0,"longitude":0},{"id":"7309112003","nama":"Bonto Manai","latitude":-5.1184596005,"longitude":119.7494212071},{"id":"7309112004","nama":"Bonto Somba","latitude":0,"longitude":0},{"id":"7309112005","nama":"Toddolimae","latitude":0,"longitude":0},{"id":"7309112006","nama":"Pucak","latitude":-5.1411057367,"longitude":119.6526412041},{"id":"7309112007","nama":"Bonto Matinggi","latitude":0,"longitude":0},{"id":"7309112008","nama":"Bonto Manurung","latitude":-5.1673176379,"longitude":119.806245149}]