[{"id":"7310031001","nama":"Mattiro Sompe","latitude":0,"longitude":0},{"id":"7310031016","nama":"Mattiro Bintang","latitude":0,"longitude":0},{"id":"7310032002","nama":"Mattiro Deceng","latitude":0,"longitude":0},{"id":"7310032003","nama":"Mattiro Langi","latitude":0,"longitude":0},{"id":"7310032009","nama":"Mattiro Matae","latitude":0,"longitude":0},{"id":"7310032010","nama":"Mattiro Ujung","latitude":0,"longitude":0},{"id":"7310032011","nama":"Mattiro Dolangeng","latitude":0,"longitude":0},{"id":"7310032013","nama":"Mattiro Bone","latitude":0,"longitude":0},{"id":"7310032015","nama":"Mattaro Adae","latitude":0,"longitude":0}]