[{"id":"9605072001","nama":"Fategomi","latitude":0,"longitude":0},{"id":"9605072002","nama":"Tehak Besar","latitude":0,"longitude":0},{"id":"9605072003","nama":"Fan","latitude":0,"longitude":0},{"id":"9605072004","nama":"Gohsames","latitude":0,"longitude":0},{"id":"9605072005","nama":"Asmuruf U","latitude":-0.3621711952,"longitude":130.3133732679},{"id":"9605072006","nama":"Mirafaan","latitude":0,"longitude":0},{"id":"9605072007","nama":"Asmuruf Tee","latitude":0,"longitude":0},{"id":"9605072008","nama":"Tehak Tee","latitude":0,"longitude":0},{"id":"9605072009","nama":"Framafir","latitude":0,"longitude":0},{"id":"9605072010","nama":"Subrit","latitude":0,"longitude":0},{"id":"9605072011","nama":"Inta","latitude":-0.1330045773,"longitude":130.4273793979},{"id":"9605072012","nama":"Bahwat","latitude":-0.2395059877,"longitude":130.5189282101}]