[{"id":"130101","nama":"Pancung Soal","latitude":0,"longitude":0},{"id":"130102","nama":"Ranah Pesisir","latitude":0,"longitude":0},{"id":"130103","nama":"Lengayang","latitude":0,"longitude":0},{"id":"130104","nama":"Batang Kapas","latitude":0,"longitude":0},{"id":"130105","nama":"IV Jurai","latitude":0,"longitude":0},{"id":"130106","nama":"Bayang","latitude":0,"longitude":0},{"id":"130107","nama":"Koto XI Tarusan","latitude":0,"longitude":0},{"id":"130108","nama":"Sutera","latitude":0,"longitude":0},{"id":"130109","nama":"Linggo Sari Baganti","latitude":0,"longitude":0},{"id":"130110","nama":"Lunang","latitude":0,"longitude":0},{"id":"130111","nama":"Basa Ampek Balai Tapan","latitude":0,"longitude":0},{"id":"130112","nama":"IV Nagari Bayang Utara","latitude":0,"longitude":0},{"id":"130113","nama":"Airpura","latitude":0,"longitude":0},{"id":"130114","nama":"Ranah Ampek Hulu Tapan","latitude":0,"longitude":0},{"id":"130115","nama":"Silaut","latitude":0,"longitude":0}]