[{"id":"140101","nama":"Bangkinang Kota","latitude":0,"longitude":0},{"id":"140102","nama":"Kampar","latitude":0,"longitude":0},{"id":"140103","nama":"Tambang","latitude":0,"longitude":0},{"id":"140104","nama":"XIII Koto Kampar","latitude":0,"longitude":0},{"id":"140105","nama":"Kuok","latitude":0,"longitude":0},{"id":"140106","nama":"Siak Hulu","latitude":0,"longitude":0},{"id":"140107","nama":"Kampar Kiri","latitude":0,"longitude":0},{"id":"140108","nama":"Kampar Kiri Hilir","latitude":0,"longitude":0},{"id":"140109","nama":"Kampar Kiri Hulu","latitude":0,"longitude":0},{"id":"140110","nama":"Tapung","latitude":0,"longitude":0},{"id":"140111","nama":"Tapung Hilir","latitude":0,"longitude":0},{"id":"140112","nama":"Tapung Hulu","latitude":0,"longitude":0},{"id":"140113","nama":"Salo","latitude":0,"longitude":0},{"id":"140114","nama":"Rumbio Jaya","latitude":0,"longitude":0},{"id":"140115","nama":"Bangkinang","latitude":0,"longitude":0},{"id":"140116","nama":"Perhentian Raja","latitude":0,"longitude":0},{"id":"140117","nama":"Kampa","latitude":0,"longitude":0},{"id":"140118","nama":"Kampar Utara","latitude":0,"longitude":0},{"id":"140119","nama":"Kampar Kiri Tengah","latitude":0,"longitude":0},{"id":"140120","nama":"Gunung Sahilan","latitude":0,"longitude":0},{"id":"140121","nama":"Koto Kampar Hulu","latitude":0,"longitude":0}]