[{"id":"810101","nama":"Amahai","latitude":0,"longitude":0},{"id":"810102","nama":"Teon Nila Serua","latitude":0,"longitude":0},{"id":"810106","nama":"Seram Utara","latitude":0,"longitude":0},{"id":"810109","nama":"Banda","latitude":0,"longitude":0},{"id":"810111","nama":"Tehoru","latitude":0,"longitude":0},{"id":"810112","nama":"Saparua","latitude":0,"longitude":0},{"id":"810113","nama":"Pulau Haruku","latitude":0,"longitude":0},{"id":"810114","nama":"Salahutu","latitude":0,"longitude":0},{"id":"810115","nama":"Leihitu","latitude":0,"longitude":0},{"id":"810116","nama":"Nusa Laut","latitude":0,"longitude":0},{"id":"810117","nama":"Kota Masohi","latitude":0,"longitude":0},{"id":"810120","nama":"Seram Utara Barat","latitude":0,"longitude":0},{"id":"810121","nama":"Teluk Elpaputih","latitude":0,"longitude":0},{"id":"810122","nama":"Leihitu Barat","latitude":0,"longitude":0},{"id":"810123","nama":"Telutih","latitude":0,"longitude":0},{"id":"810124","nama":"Seram Utara Timur Seti","latitude":0,"longitude":0},{"id":"810125","nama":"Seram Utara Timur Kobi","latitude":0,"longitude":0},{"id":"810126","nama":"Saparua Timur","latitude":0,"longitude":0}]